flake8_isolated_packages.py
flake8_isolated_packages-2.3.0.dist-info/LICENSE
flake8_isolated_packages-2.3.0.dist-info/METADATA
flake8_isolated_packages-2.3.0.dist-info/WHEEL
flake8_isolated_packages-2.3.0.dist-info/entry_points.txt
flake8_isolated_packages-2.3.0.dist-info/RECORD
