Metadata-Version: 2.1
Name: flake8-isolated-packages
Version: 2.3.0
Summary: This Flake8 plugin is for checking imports isolations.
Home-page: https://github.com/DDmitiy/flake8_isolated_packages
License: MIT
Keywords: flake8_isolated_packages,flake8,plugin,isolated_packages
Author: Dudov Dmitry
Author-email: dudov.dm@gmail.com
Requires-Python: >=3.9,<4.0
Classifier: Framework :: Flake8
Classifier: License :: OSI Approved :: MIT License
Classifier: Programming Language :: Python
Classifier: Programming Language :: Python :: 3
Classifier: Programming Language :: Python :: 3.9
Classifier: Programming Language :: Python :: 3.10
Classifier: Programming Language :: Python :: 3.11
Classifier: Topic :: Software Development :: Libraries :: Python Modules
Classifier: Topic :: Software Development :: Quality Assurance
Requires-Dist: flake8 (>=3.0)
Project-URL: Repository, https://github.com/DDmitiy/flake8_isolated_packages
